sqlalchemy_file/__init__.py
sqlalchemy_file/base.py
sqlalchemy_file/exceptions.py
sqlalchemy_file/file.py
sqlalchemy_file/helpers.py
sqlalchemy_file/mutable_list.py
sqlalchemy_file/processors.py
sqlalchemy_file/py.typed
sqlalchemy_file/storage.py
sqlalchemy_file/stored_file.py
sqlalchemy_file/types.py
sqlalchemy_file/validators.py
sqlalchemy_file-0.5.0.dist-info/METADATA
sqlalchemy_file-0.5.0.dist-info/WHEEL
sqlalchemy_file-0.5.0.dist-info/licenses/LICENSE
sqlalchemy_file-0.5.0.dist-info/RECORD
