Metadata-Version: 2.1
Name: sqlalchemy-file
Version: 0.5.0
Summary: SQLAlchemy-file is a SQLAlchemy extension for attaching files to SQLAlchemy model and uploading them to various storage.
Project-URL: Homepage, https://jowilf.github.io/sqlalchemy-file
Project-URL: Documentation, https://jowilf.github.io/sqlalchemy-file
Project-URL: Repository, https://github.com/jowilf/sqlalchemy-file
Project-URL: Changelog, https://jowilf.github.io/sqlalchemy-file/changelog/
Author-email: Jocelin Hounon <hounonj@gmail.com>
License-Expression: MIT
License-File: LICENSE
Keywords: apache-libcloud,file-upload,sqlalchemy,sqlmodel
Classifier: Development Status :: 4 - Beta
Classifier: Environment :: Web Environment
Classifier: Framework :: AsyncIO
Classifier: Intended Audience :: Developers
Classifier: License :: OSI Approved :: MIT License
Classifier: Operating System :: OS Independent
Classifier: Programming Language :: Python
Classifier: Programming Language :: Python :: 3.7
Classifier: Programming Language :: Python :: 3.8
Classifier: Programming Language :: Python :: 3.9
Classifier: Programming Language :: Python :: 3.10
Classifier: Programming Language :: Python :: 3.11
Classifier: Topic :: Database
Classifier: Topic :: Database :: Database Engines/Servers
Classifier: Topic :: Software Development :: Libraries :: Python Modules
Requires-Python: >=3.7
Requires-Dist: apache-libcloud<3.8,>=3.6
Requires-Dist: sqlalchemy<2.1,>=1.4
Provides-Extra: dev
Requires-Dist: pre-commit<4.0.0,>=2.20.0; extra == 'dev'
Requires-Dist: uvicorn<0.22.0,>=0.20.0; extra == 'dev'
Provides-Extra: doc
Requires-Dist: mkdocs-material<10.0.0,>=9.0.0; extra == 'doc'
Requires-Dist: mkdocstrings[python]<0.23.0,>=0.19.0; extra == 'doc'
Provides-Extra: test
Requires-Dist: black==23.7.0; extra == 'test'
Requires-Dist: coverage<7.3.0,>=7.0.0; extra == 'test'
Requires-Dist: fastapi<0.96,>=0.92; extra == 'test'
Requires-Dist: fasteners==0.18; extra == 'test'
Requires-Dist: flask-sqlalchemy<3.1,>=3.0; extra == 'test'
Requires-Dist: flask<2.3,>=2.2; extra == 'test'
Requires-Dist: mypy==1.4.1; extra == 'test'
Requires-Dist: pillow<10.1.0,>=9.4.0; extra == 'test'
Requires-Dist: psycopg2-binary<3.0.0,>=2.9.5; extra == 'test'
Requires-Dist: pymysql[rsa]<1.1.0,>=1.0.2; extra == 'test'
Requires-Dist: pytest<7.5.0,>=7.2.0; extra == 'test'
Requires-Dist: python-multipart==0.0.6; extra == 'test'
Requires-Dist: ruff==0.0.278; extra == 'test'
